LICENSE
pyproject.toml
HD_BET/__init__.py
HD_BET/checkpoint_download.py
HD_BET/entry_point.py
HD_BET/hd_bet_prediction.py
HD_BET/paths.py
HD_BET.egg-info/PKG-INFO
HD_BET.egg-info/SOURCES.txt
HD_BET.egg-info/dependency_links.txt
HD_BET.egg-info/entry_points.txt
HD_BET.egg-info/requires.txt
HD_BET.egg-info/top_level.txt